rename_after_writing/__init__.py
rename_after_writing/version.py
rename_after_writing-0.0.13.dist-info/licenses/LICENSE
rename_after_writing-0.0.13.dist-info/METADATA
rename_after_writing-0.0.13.dist-info/WHEEL
rename_after_writing-0.0.13.dist-info/top_level.txt
rename_after_writing-0.0.13.dist-info/RECORD
